setup.py
SimpleThreading/Threadingbyfunction.py
SimpleThreading/Threadpool.py
SimpleThreading/__init__.py
ThreadDownloader1604.egg-info/PKG-INFO
ThreadDownloader1604.egg-info/SOURCES.txt
ThreadDownloader1604.egg-info/dependency_links.txt
ThreadDownloader1604.egg-info/requires.txt
ThreadDownloader1604.egg-info/top_level.txt
htmlprocessor/Grabber.py
htmlprocessor/__init__.py